coldpack/__init__.py
coldpack/cli.py
coldpack/config/__init__.py
coldpack/config/constants.py
coldpack/config/settings.py
coldpack/core/__init__.py
coldpack/core/archiver.py
coldpack/core/extractor.py
coldpack/core/lister.py
coldpack/core/repairer.py
coldpack/core/verifier.py
coldpack/utils/__init__.py
coldpack/utils/console.py
coldpack/utils/filesystem.py
coldpack/utils/hashing.py
coldpack/utils/par2.py
coldpack/utils/progress.py
coldpack/utils/sevenzip.py
coldpack/utils/temp_manager.py
coldpack/utils/windows_compat.py
LICENSE
REUSE.toml
LICENSES/CC0-1.0.txt
LICENSES/MIT.txt
coldpack-0.5.0.dist-info/METADATA
coldpack-0.5.0.dist-info/WHEEL
coldpack-0.5.0.dist-info/entry_points.txt
coldpack-0.5.0.dist-info/licenses/LICENSE
coldpack-0.5.0.dist-info/RECORD
