Metadata-Version: 2.4
Name: coldpack
Version: 0.5.0
Summary: Professional 7z Cold Storage Solution with Revolutionary Architecture - Advanced CLI tool for creating standardized 7z archives with comprehensive verification, PAR2 recovery, and intelligent cross-platform compatibility.
Project-URL: Homepage, https://github.com/rxchi1d/coldpack
Project-URL: Repository, https://github.com/rxchi1d/coldpack
Project-URL: Issues, https://github.com/rxchi1d/coldpack/issues
Project-URL: Discussions, https://github.com/rxchi1d/coldpack/discussions
Project-URL: Documentation, https://github.com/rxchi1d/coldpack#readme
Project-URL: Changelog, https://github.com/rxchi1d/coldpack/blob/main/CHANGELOG.md
Author: coldpack contributors
Maintainer: coldpack team
License: MIT License
License-File: LICENSE
Keywords: 7z,archive,backup,blake3,cli,cold-storage,compression,cross-platform,enterprise,integrity,par2,professional,recovery,sha256,verification
Classifier: Development Status :: 5 - Production/Stable
Classifier: Environment :: Console
Classifier: Intended Audience :: Developers
Classifier: Intended Audience :: Information Technology
Classifier: Intended Audience :: System Administrators
Classifier: License :: OSI Approved :: MIT License
Classifier: Natural Language :: English
Classifier: Operating System :: MacOS
Classifier: Operating System :: Microsoft :: Windows
Classifier: Operating System :: OS Independent
Classifier: Operating System :: POSIX :: Linux
Classifier: Programming Language :: Python :: 3
Classifier: Programming Language :: Python :: 3.9
Classifier: Programming Language :: Python :: 3.10
Classifier: Programming Language :: Python :: 3.11
Classifier: Programming Language :: Python :: 3.12
Classifier: Programming Language :: Python :: 3.13
Classifier: Programming Language :: Python :: Implementation :: CPython
Classifier: Topic :: Software Development :: Libraries :: Python Modules
Classifier: Topic :: System :: Archiving :: Backup
Classifier: Topic :: System :: Archiving :: Compression
Classifier: Topic :: System :: Recovery Tools
Classifier: Topic :: System :: Systems Administration
Classifier: Topic :: Utilities
Requires-Python: >=3.9
Requires-Dist: blake3>=1.0.5
Requires-Dist: loguru>=0.7.0
Requires-Dist: par2cmdline-turbo>=1.3.0
Requires-Dist: py7zz==1.1.0
Requires-Dist: pydantic>=2.0.0
Requires-Dist: rich>=14.0.0
Requires-Dist: toml>=0.10.0
Requires-Dist: tomli>=1.2.0; python_full_version < '3.11'
Requires-Dist: typer>=0.16.0
Provides-Extra: dev
